{"status":200,"headers":{"content-type":"text/html; charset=utf-8","content-encoding":"gzip","x-nextjs-cache":"HIT","x-powered-by":"Next.js","date":"Tue, 16 Sep 2025 22:15:16 GMT","cache-control":"s-maxage=180, stale-while-revalidate=31535820","etag":"\"ks1pr8egtc9cw8\"","vary":"accept-encoding","x-cache":"Hit from cloudfront","via":"1.1 50e6d63b846cb6b459785b607dcb07c8.cloudfront.net (CloudFront)","x-amz-cf-pop":"BOS50-P2","x-amz-cf-id":"PLTAWdFt4P3q7JUL20RUBxrBcoJNB_chn_zM4UrztT0U-Cy_DhCJsg==","age":"11912"},"final_url":"https://dengekionline.com/","etag":"\"ks1pr8egtc9cw8\"","last_modified":null,"fetched_at":1758072828,"url":"https://dengekionline.com/"}