{"status":200,"headers":{"date":"Sun, 21 Sep 2025 11:32:11 GMT","content-type":"text/html; charset=UTF-8","server":"cloudflare","nel":"{\"report_to\":\"cf-nel\",\"success_fraction\":0.0,\"max_age\":604800}","vary":"Accept-Encoding","x-elasticpress-query":"true","link":"<https://getcomics.org/wp-json/>; rel=\"https://api.w.org/\"","x-cache-status":"BYPASS","x-content-type-options":"nosniff","x-frame-options":"SAMEORIGIN","referrer-policy":"no-referrer-when-downgrade","cache-control":"no-cache","report-to":"{\"group\":\"cf-nel\",\"max_age\":604800,\"endpoints\":[{\"url\":\"https://a.nel.cloudflare.com/report/v4?s=b%2FZMVw%2BLhvlXL5IbZ8IzsFxwp6ZbpyuclvfLZEdGBZ%2FCZeaHzRUNGJHQbNZ30KkNJugibmqR4pmtFWLGOjyVF%2FJ6MnrswKQOW%2B90tgX6%2F1RAQ9PwftII\"}]}","cf-cache-status":"DYNAMIC","server-timing":"cfCacheStatus;desc=\"DYNAMIC\", cfEdge;dur=6,cfOrigin;dur=3148","content-encoding":"br","cf-ray":"98293d7e7a3a80e0-EWR","alt-svc":"h3=\":443\"; ma=86400"},"final_url":"https://getcomics.org/?s=Judge+dredd+","etag":null,"last_modified":null,"fetched_at":1758454328,"url":"https://getcomics.org/?s=Judge+dredd+"}