{"status":200,"headers":{"date":"Wed, 03 Sep 2025 14:49:33 GMT","content-type":"application/rss+xml","content-encoding":"br","cf-ray":"97960ded698141bb-EWR","cf-cache-status":"DYNAMIC","cache-control":"no-cache, max-age=0","strict-transport-security":"max-age=1","via":"1.1 google","alt-svc":"h3=\":443\"; ma=86400","x-cloud-trace-context":"c8522f64288ab8c851fefaacf3d1845c","vary":"Accept-Encoding","server":"cloudflare"},"final_url":"https://www.unilad.com/index.rss","etag":null,"last_modified":null,"fetched_at":1756910972,"url":"https://www.unilad.com/index.rss"}