{"status":200,"headers":{"content-type":"text/html; charset=utf-8","x-powered-by":"Next.js","etag":"\"mu6orgemi72cnq\"","vary":"Accept-Encoding","content-encoding":"gzip","content-length":"22486","cache-control":"public, max-age=37","date":"Tue, 09 Sep 2025 14:20:56 GMT"},"final_url":"https://www.ardaudiothek.de/sendung/maushoerspiel-kurz/urn:ard:show:321c2c393a041ddc/","etag":"\"mu6orgemi72cnq\"","last_modified":null,"fetched_at":1757427656,"url":"https://www.ardaudiothek.de/sendung/maushoerspiel-kurz/urn:ard:show:321c2c393a041ddc/"}