{"status":200,"headers":{"date":"Sun, 21 Sep 2025 07:29:59 GMT","content-type":"text/html","last-modified":"Tue, 16 Sep 2025 18:50:16 GMT","x-amz-server-side-encryption":"AES256","x-amz-version-id":"5nuREr3bJOpPjXi5IepQVFDsJSf5B4AT","vary":"accept-encoding","x-cache":"Error from cloudfront","via":"1.1 52b969a4ab7956a248b07efba57c92a4.cloudfront.net (CloudFront)","x-amz-cf-pop":"EWR53-P1","x-amz-cf-id":"puVJ3T7lPcQbaoMPoL0btZ95JVJZJC057JE0wlgkkPIEIaP-7OQXjg==","age":"51","cf-cache-status":"DYNAMIC","set-cookie":"__cf_bm=pjm7PwphVFxNXsC6gZh13VVk_xPyds9A_KdGtQ2VZWg-1758439799-1.0.1.1-VTfYs4azycAN0Jmj_H8YVOiyBpXQ_YTHlxM_FyvOF_LufZ4L2MAqcDMpTxUwwrXABoyZeMFxRJnH51s0mWY6LVEmNs709oB_7KUnJZQGBn99.CP7ZJTSVTQX1tq6WuQV; path=/; expires=Sun, 21-Sep-25 07:59:59 GMT; domain=.crunchyroll.com; HttpOnly; Secure; SameSite=None","server":"cloudflare","cf-ray":"9827dac99afc43e8-EWR","content-encoding":"gzip","alt-svc":"h3=\":443\"; ma=86400"},"final_url":"https://www.crunchyroll.com/news/latest","etag":null,"last_modified":"Tue, 16 Sep 2025 18:50:16 GMT","fetched_at":1758439799,"url":"https://www.crunchyroll.com/news/latest"}